grafcet/__init__.py
grafcet/grafcet.py
grafcet/temporisation.py
grafcet-0.1.2.dist-info/WHEEL
grafcet-0.1.2.dist-info/METADATA
grafcet-0.1.2.dist-info/RECORD
