Metadata-Version: 2.1
Name: grafcet
Version: 0.1.2
Summary: 
Author: Pierre Lemaitre
Author-email: oultetman@sfr.fr
Requires-Python: >=3.09,<4.0
Classifier: Programming Language :: Python :: 3
Classifier: Programming Language :: Python :: 3.10
Classifier: Programming Language :: Python :: 3.9
Requires-Dist: multipledispatch (>=0.6.0,<0.7.0)
